shift_counter/__init__.py
shift_counter/shiftcounter.py
shift_counter/unitfilter.py
shift_counter/unitorganiser.py
shift_counter-1.1.4.dist-info/LICENSE
shift_counter-1.1.4.dist-info/METADATA
shift_counter-1.1.4.dist-info/WHEEL
shift_counter-1.1.4.dist-info/top_level.txt
shift_counter-1.1.4.dist-info/RECORD
