Metadata-Version: 2.1
Name: shift_counter
Version: 1.1.4
Summary: Library for processing attendance plan data into time-segmented DataFrames
Home-page: https://github.com/daniel-simanek/shift-counter
Author: Daniel Simanek
Author-email: daniel.simanek@decathlon.com
Classifier: Development Status :: 5 - Production/Stable
Classifier: Intended Audience :: Developers
Classifier: Programming Language :: Python :: 3
Classifier: Programming Language :: Python :: 3.7
Classifier: Programming Language :: Python :: 3.8
Classifier: Programming Language :: Python :: 3.9
Classifier: Programming Language :: Python :: 3.10
Classifier: License :: OSI Approved :: MIT License
Classifier: Operating System :: OS Independent
Classifier: Topic :: Office/Business
Classifier: Topic :: Software Development :: Libraries :: Python Modules
Requires-Python: >=3.7
License-File: LICENSE
Requires-Dist: pandas>=1.0.0
